corankco/__init__.py
corankco/consensus.py
corankco/dataset.py
corankco/element.py
corankco/kemeny_score_computation.py
corankco/ranking.py
corankco/scoringscheme.py
corankco/utils.py
corankco/algorithms/__init__.py
corankco/algorithms/algorithm_choice.py
corankco/algorithms/pairwisebasedalgorithm.py
corankco/algorithms/rank_aggregation_algorithm.py
corankco/algorithms/bioconsert/__init__.py
corankco/algorithms/bioconsert/bioco.py
corankco/algorithms/bioconsert/bioconsert.py
corankco/algorithms/borda/__init__.py
corankco/algorithms/borda/borda.py
corankco/algorithms/copeland/__init__.py
corankco/algorithms/copeland/copeland.py
corankco/algorithms/exact/__init__.py
corankco/algorithms/exact/exactalgorithm.py
corankco/algorithms/exact/exactalgorithmbase.py
corankco/algorithms/exact/exactalgorithmcplex.py
corankco/algorithms/exact/exactalgorithmcplexforpaperoptim1.py
corankco/algorithms/exact/exactalgorithmpulp.py
corankco/algorithms/kwiksort/__init__.py
corankco/algorithms/kwiksort/kwiksortabs.py
corankco/algorithms/kwiksort/kwiksortrandom.py
corankco/algorithms/parcons/__init__.py
corankco/algorithms/parcons/parcons.py
corankco/algorithms/pickaperm/__init__.py
corankco/algorithms/pickaperm/pickaperm.py
corankco/partitioning/__init__.py
corankco/partitioning/ordered_partition.py
corankco-7.2.0.dist-info/LICENSE
corankco-7.2.0.dist-info/METADATA
corankco-7.2.0.dist-info/WHEEL
corankco-7.2.0.dist-info/top_level.txt
corankco-7.2.0.dist-info/RECORD
