Metadata-Version: 2.1
Name: corankco
Version: 7.2.0
Summary: Kemeny-Young method for rank aggregation of incomplete rankings with ties
Home-page: https://github.com/pierreandrieu/corankco
Author: Pierre Andrieu
Author-email: pierre.andrieu@lilo.org
License: GPLv2
Requires-Python: >=3.8
License-File: LICENSE
Requires-Dist: numpy (>=1.24)
Requires-Dist: python-igraph
Requires-Dist: pulp (>=2.7)
Requires-Dist: numba (>=0.57.1)
Requires-Dist: setuptools (>=68.0.0)
